mlogevo/__init__.py
mlogevo/__main__.py
mlogevo/backend/__init__.py
mlogevo/backend/asm_template.py
mlogevo/backend/backend.py
mlogevo/backend/basic_block.py
mlogevo/backend/inline_utils.py
mlogevo/frontend/__init__.py
mlogevo/frontend/abstract_compiler.py
mlogevo/frontend/compilation_error.py
mlogevo/frontend/compiler.py
mlogevo/frontend/compiler_sketch.py
mlogevo/frontend/mlog_object.py
mlogevo/frontend/parent_node_visitor.py
mlogevo/frontend/type_util.py
mlogevo/frontend/components/__init__.py
mlogevo/frontend/components/branch_support.py
mlogevo/intermediate/__init__.py
mlogevo/intermediate/function.py
mlogevo/intermediate/ir_quadruple.py
mlogevo/intermediate/quadruple_from_text.py
mlogevo/optimizer/__init__.py
mlogevo/optimizer/mi_deduplicate_tail_return.py
mlogevo/optimizer/mi_lcse.py
mlogevo/optimizer/mi_remove_unused_decls.py
mlogevo/optimizer/mi_remove_unused_labels.py
mlogevo/optimizer/mi_remove_unused_variables.py
mlogevo/optimizer/mi_reorder_decls.py
mlogevo/optimizer/optimizer_registry.py
mlogevo/output/__init__.py
mlogevo/output/abstract_ir_converter.py
mlogevo/output/ir_output.py
mlogevo/output/mlog_instructions.py
mlogevo/output/mlog_output.py
mlogevo-0.0.11.dist-info/LICENSE
mlogevo-0.0.11.dist-info/METADATA
mlogevo-0.0.11.dist-info/WHEEL
mlogevo-0.0.11.dist-info/entry_points.txt
mlogevo-0.0.11.dist-info/top_level.txt
mlogevo-0.0.11.dist-info/RECORD
