Metadata-Version: 2.1
Name: mlogevo
Version: 0.0.11
Summary: Compile C code to Mindustry logic
Home-page: https://github.com/UMRnInside/MlogEvo
Author: UMRnInside
Author-email: 30196401+UMRnInside@users.noreply.github.com
Project-URL: Bug Tracker, https://github.com/UMRnInside/MlogEvo/issues
Classifier: Programming Language :: Python :: 3
Classifier: License :: OSI Approved :: MIT License
Classifier: Operating System :: OS Independent
Requires-Python: >=3.7
License-File: LICENSE
Requires-Dist: pycparserext-gnuc (>=2022.10)
Requires-Dist: pycparser (>=2.21)
